[
  {
    "context": {
      "ttl": "PT10M",
      "action": "init",
      "timestamp": "2024-09-27T12:08:36.887Z",
      "message_id": "0fe65aa7-159c-46b7-ab11-3ef6abba97c7",
      "transaction_id": "ead489b8-81de-49a4-baf6-8d8de7eabf38",
      "domain": "Software Assurance",
      "version": "1.1.0",
      "bap_id": "bap.ossverse.com",
      "bap_uri": "http://bap.ossverse.com",
      "location": {
        "country": {
          "name": "India",
          "code": "IND"
        },
        "city": {
          "name": "Bengaluru",
          "code": "std:080"
        }
      },
      "bpp_id": "openfort-oasp.ossverse.com",
      "bpp_uri": "http://openfort-oasp.ossverse.com"
    },
    "message": {
      "catalogs": {
        "context": {
          "ttl": "PT10M",
          "action": "init",
          "timestamp": "2024-09-27T12:08:36.887Z",
          "message_id": "0fe65aa7-159c-46b7-ab11-3ef6abba97c7",
          "transaction_id": "ead489b8-81de-49a4-baf6-8d8de7eabf38",
          "domain": "Software Assurance",
          "version": "1.1.0",
          "bap_id": "bap.ossverse.com",
          "bap_uri": "http://bap.ossverse.com",
          "location": {
            "country": {
              "name": "India",
              "code": "IND"
            },
            "city": {
              "name": "Bengaluru",
              "code": "std:080"
            }
          },
          "bpp_id": "openfort-oasp.ossverse.com",
          "bpp_uri": "http://openfort-oasp.ossverse.com"
        },
        "responses": [
          {
            "context": {
              "domain": "Software Assurance",
              "action": "on_init",
              "version": "1.1.0",
              "bpp_id": "openfort-oasp.ossverse.com",
              "bpp_uri": "http://openfort-oasp.ossverse.com",
              "country": "IND",
              "city": "std:080",
              "location": {
                "country": {
                  "name": "India",
                  "code": "IND"
                },
                "city": {
                  "name": "Bengaluru",
                  "code": "std:080"
                }
              },
              "bap_id": "bap.ossverse.com",
              "bap_uri": "http://bap.ossverse.com",
              "transaction_id": "ead489b8-81de-49a4-baf6-8d8de7eabf38",
              "message_id": "0fe65aa7-159c-46b7-ab11-3ef6abba97c7",
              "ttl": "PT10M",
              "timestamp": "2024-09-27T12:08:42.731Z"
            },
            "message": {
              "order": {
                "provider": {
                  "id": "ceae624e-be6a-4ec5-b483-b23b3a715aa5"
                },
                "provider_location": {},
                "items": [
                  {
                    "id": "e2b41750-a165-4a42-9255-f02966401783"
                  }
                ],
                "billing": {
                  "name": "Name",
                  "address": "address",
                  "state": {
                    "name": "Name"
                  },
                  "city": {
                    "name": "Name"
                  },
                  "email": "example@gmail.com",
                  "phone": "123456789"
                },
                "fulfillments": [],
                "quote": {
                  "price": {
                    "value": "11000",
                    "currency": "INR"
                  },
                  "breakup": [
                    {
                      "@ondc/org/item_id": "e2b41750-a165-4a42-9255-f02966401783",
                      "@ondc/org/item_quantity": {
                        "count": 1
                      },
                      "title": "beep",
                      "@ondc/org/title_type": "item",
                      "price": {
                        "value": "11000",
                        "currency": "INR"
                      },
                      "item": {
                        "price": {
                          "value": "11000",
                          "currency": "INR"
                        }
                      }
                    },
                    {
                      "title": "Delivery charges",
                      "@ondc/org/title_type": "delivery",
                      "@ondc/org/item_id": "fullfillment_id_0",
                      "price": {
                        "currency": "INR",
                        "value": "0"
                      }
                    }
                  ],
                  "ttl": "P1D"
                },
                "payment": {
                  "@ondc/org/buyer_app_finder_fee_type": "Percent",
                  "@ondc/org/buyer_app_finder_fee_amount": "3.0",
                  "@ondc/org/settlement_details": [
                    {
                      "settlement_counterparty": "seller-app",
                      "settlement_phase": "sale-amount",
                      "settlement_type": "neft",
                      "settlement_bank_account_no": "1234567890",
                      "settlement_ifsc_code": "IFSC0001234",
                      "beneficiary_name": "openfort",
                      "bank_name": "Bank of Springfield",
                      "branch_name": "Main Branch"
                    }
                  ]
                },
                "type": "DEFAULT"
              }
            }
          }
        ]
      }
    }
  }
]